[{"SpawnId":"1f657236-bdc7-4e7f-ba00-39ee8d995cb3","Team":2,"BombSite":0,"IsInBombZone":true,"PositionX":1108.9817,"PositionY":1984.1704,"PositionZ":-191.96875,"QAngleX":0,"QAngleY":-38.369064,"QAngleZ":0},{"SpawnId":"133237b1-9f78-4560-898a-d123a525ac15","Team":2,"BombSite":0,"IsInBombZone":true,"PositionX":988.8572,"PositionY":1781.054,"PositionZ":-191.96875,"QAngleX":0,"QAngleY":-53.352013,"QAngleZ":0},{"SpawnId":"c94383c0-bf36-4557-8893-f46351d27f5d","Team":2,"BombSite":0,"IsInBombZone":true,"PositionX":1333.4309,"PositionY":2157.2332,"PositionZ":-191.96875,"QAngleX":0,"QAngleY":-14.875488,"QAngleZ":0},{"SpawnId":"d4a22004-9eba-4c9b-ace6-18ab020c30d7","Team":2,"BombSite":0,"IsInBombZone":false,"PositionX":1499.0504,"PositionY":1925.9319,"PositionZ":-149.96875,"QAngleX":0,"QAngleY":-74.441986,"QAngleZ":0},{"SpawnId":"bea8878a-2116-47e6-b8b2-363a11e592b6","Team":2,"BombSite":0,"IsInBombZone":false,"PositionX":1269.9283,"PositionY":1831.5443,"PositionZ":-191.96875,"QAngleX":0,"QAngleY":-140.9285,"QAngleZ":0},{"SpawnId":"b76c2914-c823-4168-a022-fba57110da9c","Team":2,"BombSite":0,"IsInBombZone":false,"PositionX":1106.4062,"PositionY":1698.1268,"PositionZ":-153.8487,"QAngleX":0,"QAngleY":-100.537605,"QAngleZ":0},{"SpawnId":"25b04e97-7ea2-4d43-aaa3-cec73fc03c58","Team":2,"BombSite":0,"IsInBombZone":false,"PositionX":1451.0693,"PositionY":1582.6781,"PositionZ":-151.96875,"QAngleX":0,"QAngleY":-37.558823,"QAngleZ":0},{"SpawnId":"cfb36d86-9595-41cc-bb2a-7af1e5c8b931","Team":2,"BombSite":0,"IsInBombZone":false,"PositionX":1626.0265,"PositionY":1848.3428,"PositionZ":-70.46875,"QAngleX":0,"QAngleY":-80.00004,"QAngleZ":0},{"SpawnId":"7ef12d09-972c-48e9-90f2-b73318e4f069","Team":2,"BombSite":0,"IsInBombZone":false,"PositionX":1426.0651,"PositionY":1906.8093,"PositionZ":-149.96875,"QAngleX":0,"QAngleY":-139.26852,"QAngleZ":0},{"SpawnId":"8b3bd3fa-f840-45e7-9a64-528311ea926d","Team":3,"BombSite":0,"IsInBombZone":false,"PositionX":1214.9429,"PositionY":889.9454,"PositionZ":-151.96875,"QAngleX":0,"QAngleY":3.850708,"QAngleZ":0},{"SpawnId":"d7606926-ce02-4df4-ba1e-2fb3d0e1198d","Team":3,"BombSite":0,"IsInBombZone":false,"PositionX":1185.5087,"PositionY":671.7269,"PositionZ":-148.96875,"QAngleX":0,"QAngleY":70.29053,"QAngleZ":0},{"SpawnId":"f60307b9-b151-4edc-add5-e00c733bf785","Team":3,"BombSite":0,"IsInBombZone":false,"PositionX":1236.8413,"PositionY":491.84686,"PositionZ":-35.96875,"QAngleX":0,"QAngleY":107.88541,"QAngleZ":0},{"SpawnId":"fb2c0450-651e-4087-b533-72a9fd6ea043","Team":3,"BombSite":0,"IsInBombZone":false,"PositionX":133.17699,"PositionY":1602.817,"PositionZ":-31.96875,"QAngleX":0,"QAngleY":-47.450287,"QAngleZ":0},{"SpawnId":"4c33e29b-14aa-4138-8358-41084cce40ff","Team":3,"BombSite":0,"IsInBombZone":false,"PositionX":-102.4151,"PositionY":1592.963,"PositionZ":27.03125,"QAngleX":0,"QAngleY":-12.3918915,"QAngleZ":0},{"SpawnId":"3dcef8da-0fcc-4ddf-a702-1541930b7f80","Team":3,"BombSite":0,"IsInBombZone":false,"PositionX":-9.175583,"PositionY":808.3923,"PositionZ":0.26654434,"QAngleX":0,"QAngleY":40.03212,"QAngleZ":0},{"SpawnId":"caf1129a-9e51-44c9-b62b-d6da01bb341c","Team":3,"BombSite":0,"IsInBombZone":false,"PositionX":336.60797,"PositionY":580.81683,"PositionZ":-30.900635,"QAngleX":0,"QAngleY":176.5115,"QAngleZ":0},{"SpawnId":"a3c7e943-c1ee-4eca-9b0b-21baf0480d89","Team":3,"BombSite":0,"IsInBombZone":false,"PositionX":171.5248,"PositionY":515.20856,"PositionZ":-28.96875,"QAngleX":0,"QAngleY":60.353394,"QAngleZ":0},{"SpawnId":"b2901a4a-7921-4adb-a4c0-e8ec3c465433","Team":3,"BombSite":0,"IsInBombZone":false,"PositionX":-196.93018,"PositionY":2533.7715,"PositionZ":-94.96875,"QAngleX":0,"QAngleY":6.9062805,"QAngleZ":0},{"SpawnId":"e85dd978-b787-45dc-a18f-86af91b7ffc4","Team":3,"BombSite":0,"IsInBombZone":false,"PositionX":36.788372,"PositionY":2707.727,"PositionZ":-108.86786,"QAngleX":0,"QAngleY":-41.59149,"QAngleZ":0},{"SpawnId":"ebbe6629-1b7a-441c-af91-a38bdb554933","Team":2,"BombSite":1,"IsInBombZone":true,"PositionX":-1144.1047,"PositionY":769.7596,"PositionZ":-3.96875,"QAngleX":0,"QAngleY":-86.30859,"QAngleZ":0},{"SpawnId":"a91bc508-f8bc-423e-ae2c-f16f5fe66994","Team":2,"BombSite":1,"IsInBombZone":true,"PositionX":-1136.0312,"PositionY":689.3557,"PositionZ":-1.96875,"QAngleX":0,"QAngleY":89.40845,"QAngleZ":0},{"SpawnId":"58302d34-1433-4529-8bb5-a8666881d0e9","Team":2,"BombSite":1,"IsInBombZone":true,"PositionX":-879.2152,"PositionY":541.86957,"PositionZ":0.03125,"QAngleX":0,"QAngleY":98.33176,"QAngleZ":0},{"SpawnId":"401c5f18-e594-42ba-a146-712909cf3b2d","Team":2,"BombSite":1,"IsInBombZone":false,"PositionX":-717.7428,"PositionY":854.38477,"PositionZ":38.03125,"QAngleX":0,"QAngleY":179.72397,"QAngleZ":0},{"SpawnId":"b2d26a4c-e7c9-4a93-b499-b6b4dcab36c3","Team":2,"BombSite":1,"IsInBombZone":false,"PositionX":-692.10065,"PositionY":677.18475,"PositionZ":38.03125,"QAngleX":0,"QAngleY":-134.87503,"QAngleZ":0},{"SpawnId":"304f4e20-023e-4d1c-acb0-897bfabade79","Team":2,"BombSite":1,"IsInBombZone":false,"PositionX":-1142.7283,"PositionY":272.76178,"PositionZ":-22.96875,"QAngleX":0,"QAngleY":2.163971,"QAngleZ":0},{"SpawnId":"949186fb-baa1-4e28-b586-97f66b2f965d","Team":2,"BombSite":1,"IsInBombZone":false,"PositionX":-1308.7422,"PositionY":292.44644,"PositionZ":1.0312481,"QAngleX":0,"QAngleY":128.91565,"QAngleZ":0},{"SpawnId":"18d91241-61f3-4e02-b724-4ff70226726b","Team":2,"BombSite":1,"IsInBombZone":false,"PositionX":-1518.7567,"PositionY":771.0877,"PositionZ":38.031254,"QAngleX":0,"QAngleY":-32.93495,"QAngleZ":0},{"SpawnId":"db2e72e8-ee4e-48fa-8c46-a2a71550eb2a","Team":2,"BombSite":1,"IsInBombZone":false,"PositionX":-1009.58154,"PositionY":782.9357,"PositionZ":-1.96875,"QAngleX":0,"QAngleY":65.41293,"QAngleZ":0},{"SpawnId":"aa382531-7c65-4318-aa6a-8199c9615b36","Team":3,"BombSite":1,"IsInBombZone":false,"PositionX":-276.22876,"PositionY":1559.3865,"PositionZ":27.031246,"QAngleX":0,"QAngleY":-64.02557,"QAngleZ":0},{"SpawnId":"20f5d298-946f-48f1-8212-24168174f41d","Team":3,"BombSite":1,"IsInBombZone":false,"PositionX":-139.56885,"PositionY":1536.3218,"PositionZ":27.031246,"QAngleX":0,"QAngleY":-107.03705,"QAngleZ":0},{"SpawnId":"7dfb06b4-a1de-4c4f-872c-cc7edbe8167d","Team":3,"BombSite":1,"IsInBombZone":false,"PositionX":-12.502686,"PositionY":1572.5043,"PositionZ":-1.984314,"QAngleX":0,"QAngleY":-156.55002,"QAngleZ":0},{"SpawnId":"71c3fe85-79e2-4547-b4db-1abd8c64d699","Team":3,"BombSite":1,"IsInBombZone":false,"PositionX":-531.44586,"PositionY":1975.3077,"PositionZ":16.056595,"QAngleX":0,"QAngleY":-177.28879,"QAngleZ":0},{"SpawnId":"c41aae9e-62a1-492d-8771-aee3c0770211","Team":3,"BombSite":1,"IsInBombZone":false,"PositionX":-888.7193,"PositionY":2027.1996,"PositionZ":16.056595,"QAngleX":0,"QAngleY":-82.515564,"QAngleZ":0},{"SpawnId":"284929f6-6759-4ffd-91ce-1a5d1716edde","Team":3,"BombSite":1,"IsInBombZone":false,"PositionX":-753.9686,"PositionY":2170.454,"PositionZ":16.056595,"QAngleX":0,"QAngleY":-114.91253,"QAngleZ":0},{"SpawnId":"cbdf7977-747c-4cd9-96bf-653b0cb28944","Team":3,"BombSite":1,"IsInBombZone":false,"PositionX":-237.64015,"PositionY":1779.7229,"PositionZ":27.031246,"QAngleX":0,"QAngleY":-82.56569,"QAngleZ":0},{"SpawnId":"4205ecd5-851c-4d44-b075-9ad428088bde","Team":3,"BombSite":1,"IsInBombZone":false,"PositionX":668.4304,"PositionY":119.70211,"PositionZ":-148.96875,"QAngleX":0,"QAngleY":169.69345,"QAngleZ":0},{"SpawnId":"8e7d3057-c749-42a4-9170-7d3d851a7978","Team":3,"BombSite":1,"IsInBombZone":false,"PositionX":263.45468,"PositionY":346.49225,"PositionZ":-151.96875,"QAngleX":0,"QAngleY":-153.09003,"QAngleZ":0},{"SpawnId":"43c019a1-df02-444a-9014-ba645abb8b7d","Team":3,"BombSite":1,"IsInBombZone":false,"PositionX":331.45984,"PositionY":48.81616,"PositionZ":-151.96875,"QAngleX":0,"QAngleY":179.31403,"QAngleZ":0},{"SpawnId":"81ee9d7c-a45f-42a1-8bdd-3a7dece863fe","Team":3,"BombSite":1,"IsInBombZone":false,"PositionX":-705.1714,"PositionY":-557.7611,"PositionZ":80.28895,"QAngleX":0,"QAngleY":-159.6746,"QAngleZ":0},{"SpawnId":"45bc437d-25a3-4869-8db8-4caf0445baa1","Team":3,"BombSite":1,"IsInBombZone":false,"PositionX":-1048.3593,"PositionY":-931.87213,"PositionZ":64.03125,"QAngleX":0,"QAngleY":84.35474,"QAngleZ":0},{"SpawnId":"efc65381-b5e7-4dce-9143-a1f6e173faca","Team":3,"BombSite":1,"IsInBombZone":false,"PositionX":-991.2933,"PositionY":-683.51904,"PositionZ":64.03125,"QAngleX":0,"QAngleY":123.045166,"QAngleZ":0}]